chcss/__init__.py
chcss/config.py
chcss/parser.py
chcss-0.0.1.dist-info/LICENSE.rst
chcss-0.0.1.dist-info/METADATA
chcss-0.0.1.dist-info/WHEEL
chcss-0.0.1.dist-info/entry_points.txt
chcss-0.0.1.dist-info/top_level.txt
chcss-0.0.1.dist-info/RECORD
