Metadata-Version: 2.1
Name: chcss
Version: 0.0.1
Summary: CSS naming hierarchy enforcer
Home-page: https://github.com/jeremyagray/chcss
Author: Jeremy A Gray
Author-email: jeremy.a.gray@gmail.com
Maintainer: Jeremy A Gray
Maintainer-email: jeremy.a.gray@gmail.com
License: GPL-3.0-or-later
Project-URL: Issues, https://github.com/jeremyagray/chcss/issues
Project-URL: Documentation, https://chcss.readthedocs.io/
Project-URL: Repository, https://github.com/jeremyagray/chcss
Platform: UNKNOWN
Classifier: Development Status :: 3 - Alpha
Classifier: Environment :: Console
Classifier: License :: OSI Approved :: GNU General Public License v3 or later (GPLv3+)
Classifier: Intended Audience :: Developers
Classifier: Programming Language :: Python :: 3.6
Classifier: Programming Language :: Python :: 3.7
Classifier: Programming Language :: Python :: 3.8
Classifier: Programming Language :: Python :: 3.9
Classifier: Topic :: Text Processing :: Markup :: HTML
Requires-Dist: pyparsing
Requires-Dist: toml
